{
  "id": 132,
  "ref": "QL.14;HCM;QL.19",
  "hData": {
    "trunks-QL.14;HCM;QL.19-6": {
      "id": "trunks-QL.14;HCM;QL.19-6",
      "name": "Quốc lộ QL.14;HCM;QL.19",
      "highway_id": 1,
      "way_id": 0,
      "key": "1-0",
      "nodes": [
        [
          13.9077599,
          108.0143219
        ],
        [
          13.9064478,
          108.0156094
        ],
        [
          13.9049794,
          108.0168995
        ],
        [
          13.903792,
          108.017436
        ],
        [
          13.9032195,
          108.0176157
        ],
        [
          13.9025763,
          108.0177927
        ],
        [
          13.9016624,
          108.0177122
        ],
        [
          13.9004282,
          108.0171409
        ],
        [
          13.8991187,
          108.0165642
        ],
        [
          13.8982313,
          108.0161753
        ],
        [
          13.8972286,
          108.0156711
        ],
        [
          13.8954944,
          108.0149066
        ],
        [
          13.8937579,
          108.014161
        ],
        [
          13.8928752,
          108.0137479
        ],
        [
          13.8916098,
          108.0131525
        ],
        [
          13.8906541,
          108.0127206
        ],
        [
          13.8894433,
          108.0121949
        ],
        [
          13.8882586,
          108.0116853
        ],
        [
          13.887157,
          108.0111784
        ],
        [
          13.8861648,
          108.0106446
        ],
        [
          13.8860894,
          108.010886
        ],
        [
          13.886753,
          108.0110899
        ],
        [
          13.8880056,
          108.0116692
        ],
        [
          13.8890498,
          108.0121279
        ],
        [
          13.8901018,
          108.012608
        ],
        [
          13.8913905,
          108.0131981
        ],
        [
          13.8923748,
          108.0136219
        ],
        [
          13.8933069,
          108.0140564
        ],
        [
          13.8942755,
          108.0144748
        ],
        [
          13.8951763,
          108.0149066
        ],
        [
          13.8962226,
          108.0153707
        ],
        [
          13.8972932,
          108.0158454
        ],
        [
          13.8984051,
          108.0163577
        ],
        [
          13.9000739,
          108.0171061
        ],
        [
          13.9009826,
          108.0175111
        ],
        [
          13.9017637,
          108.0178383
        ],
        [
          13.9024979,
          108.0179107
        ],
        [
          13.9030082,
          108.0178437
        ],
        [
          13.9037164,
          108.0175835
        ],
        [
          13.9047761,
          108.0171651
        ],
        [
          13.9054687,
          108.0167279
        ],
        [
          13.9062524,
          108.0159688
        ],
        [
          13.9071971,
          108.0150703
        ],
        [
          13.9078848,
          108.014397
        ]
      ],
      "bounds": [
        [
          13.885955009368926,
          108.01050626023046
        ],
        [
          13.885955009368926,
          108.0180490366757
        ],
        [
          13.908019654386624,
          108.0180490366757
        ],
        [
          13.908019654386624,
          108.01050626023046
        ]
      ],
      "maxSpeed": "0",
      "minSpeed": "",
      "lanes": "0",
      "buffer_geometry": [
        [
          13.907879336412146,
          108.01425874044158
        ],
        [
          13.907873853430448,
          108.01424752471122
        ],
        [
          13.907857579320503,
          108.0142260511786
        ],
        [
          13.907837551448186,
          108.01420826106705
        ],
        [
          13.907814539474263,
          108.01419483804028
        ],
        [
          13.907789427736734,
          108.0141862979368
        ],
        [
          13.90776318126611,
          108.01418296894653
        ],
        [
          13.907736808699745,
          108.01418497899894
        ],
        [
          13.90771132352045,
          108.0141922508471
        ],
        [
          13.907687705108925,
          108.01420450503639
        ],
        [
          13.90766686110678,
          108.01422127064413
        ],
        [
          13.906357445115033,
          108.01550613754804
        ],
        [
          13.904907000652175,
          108.0167804630112
        ],
        [
          13.90374508806629,
          108.01730544770763
        ],
        [
          13.903182423042454,
          108.01748206096059
        ],
        [
          13.902564282451255,
          108.01765216532203
        ],
        [
          13.901696757127079,
          108.01757575070968
        ],
        [
          13.900483489042125,
          108.01701414062369
        ],
        [
          13.90048122688481,
          108.01701311903719
        ],
        [
          13.899171726584896,
          108.01643641962775
        ],
        [
          13.899171507872316,
          108.01643632354286
        ],
        [
          13.89828732835399,
          108.01604883539028
        ],
        [
          13.897287773399105,
          108.01554621739875
        ],
        [
          13.897281672394895,
          108.0155433408553
        ],
        [
          13.895547471997446,
          108.01477884163683
        ],
        [
          13.895546298773045,
          108.01477833117707
        ],
        [
          13.89381176094683,
          108.01403357462827
        ],
        [
          13.892931121544628,
          108.01362143946426
        ],
        [
          13.89166584612466,
          108.0130260987729
        ],
        [
          13.891663994472463,
          108.01302524481062
        ],
        [
          13.890708294248855,
          108.01259334523459
        ],
        [
          13.890706493324496,
          108.01259254738935
        ],
        [
          13.889495693050627,
          108.01206684793978
        ],
        [
          13.889495280279618,
          108.01206666955608
        ],
        [
          13.88831210758934,
          108.0115577271813
        ],
        [
          13.887215789150975,
          108.01105325808096
        ],
        [
          13.886227249169348,
          108.0105214276927
        ],
        [
          13.886203100382174,
          108.01051135926951
        ],
        [
          13.886177523134851,
          108.01050626023046
        ],
        [
          13.886151471363513,
          108.01050632074906
        ],
        [
          13.88612591670194,
          108.01051153856648
        ],
        [
          13.88610181224326,
          108.01052171907604
        ],
        [
          13.886080056993194,
          108.0105364825815
        ],
        [
          13.886061462340557,
          108.01055527845857
        ],
        [
          13.886046721795628,
          108.01057740569121
        ],
        [
          13.886036385124909,
          108.01060203901685
        ],
        [
          13.885960985166696,
          108.01084343889688
        ],
        [
          13.885955351106212,
          108.01087043283049
        ],
        [
          13.885955009368926,
          108.01089804136367
        ],
        [
          13.885959973446798,
          108.01092517449784
        ],
        [
          13.88597004735556,
          108.0109507610032
        ],
        [
          13.885984833372214,
          108.0109737907114
        ],
        [
          13.886003747737291,
          108.01099335439724
        ],
        [
          13.886026043701861,
          108.01100867967536
        ],
        [
          13.886050841009453,
          108.01101916149433
        ],
        [
          13.886705889819158,
          108.01122043439516
        ],
        [
          13.887950348924988,
          108.01179597011357
        ],
        [
          13.887952684560231,
          108.01179702309669
        ],
        [
          13.888996019079054,
          108.01225534347876
        ],
        [
          13.890047082323541,
          108.01273501655102
        ],
        [
          13.891335705566513,
          108.01332508211034
        ],
        [
          13.89133847843077,
          108.0133263137238
        ],
        [
          13.892320970627255,
          108.01374933589655
        ],
        [
          13.893251285523231,
          108.01418300427946
        ],
        [
          13.893254734504898,
          108.01418455271487
        ],
        [
          13.894220941169149,
          108.01460191941072
        ],
        [
          13.895119388194537,
          108.01503259200199
        ],
        [
          13.89512295076724,
          108.01503423556595
        ],
        [
          13.896169250526194,
          108.01549833603568
        ],
        [
          13.897238993110063,
          108.01597265644972
        ],
        [
          13.89835002370094,
          108.0164845564864
        ],
        [
          13.898351255357122,
          108.01648511638608
        ],
        [
          13.900020054969033,
          108.01723351713032
        ],
        [
          13.90002033596012,
          108.01723364275566
        ],
        [
          13.900929035749881,
          108.01763864316248
        ],
        [
          13.900931787059045,
          108.01763983236802
        ],
        [
          13.901712886887601,
          108.0179670327305
        ],
        [
          13.901750846000041,
          108.01797663624102
        ],
        [
          13.90248504595925,
          108.0180490366757
        ],
        [
          13.902514954612908,
          108.01804855393615
        ],
        [
          13.903025254650467,
          108.01798155423509
        ],
        [
          13.903053515038525,
          108.01797459386523
        ],
        [
          13.903761715177106,
          108.01771439421475
        ],
        [
          13.903764676642545,
          108.01771326572094
        ],
        [
          13.904824376863472,
          108.01729486622777
        ],
        [
          13.904846579321676,
          108.0172835947236
        ],
        [
          13.905539179532505,
          108.01684639494505
        ],
        [
          13.905561104449465,
          108.01682914692492
        ],
        [
          13.906344357274005,
          108.0160704804084
        ],
        [
          13.907288606346347,
          108.01517240969773
        ],
        [
          13.907290029271223,
          108.01517103659839
        ],
        [
          13.907977729547277,
          108.01449773662739
        ],
        [
          13.907995020521511,
          108.01447712378851
        ],
        [
          13.908008075781412,
          108.01445343183306
        ],
        [
          13.908016393619913,
          108.01442757123047
        ],
        [
          13.908019654386624,
          108.01440053579066
        ],
        [
          13.908017732771894,
          108.01437336447216
        ],
        [
          13.90801070262243,
          108.01434710145529
        ],
        [
          13.907998834103378,
          108.01432275601461
        ],
        [
          13.907982583315965,
          108.0143012637328
        ],
        [
          13.907962574769694,
          108.01428345054667
        ],
        [
          13.907939577382628,
          108.01427000100668
        ],
        [
          13.907914474932218,
          108.0142614319702
        ],
        [
          13.907888232092066,
          108.01425807273907
        ],
        [
          13.907879336412146,
          108.01425874044158
        ]
      ]
    }
  },
  "keyData": {
    "13.95_108.01__13.96_108.02": [
      "trunks-QL.14;HCM;QL.19-0",
      "trunks-QL.14;HCM;QL.19-3",
      "trunks-QL.14;HCM;QL.19-4",
      "trunks-QL.14;HCM;QL.19-5",
      "trunks-QL.14;HCM;QL.19-0",
      "trunks-QL.14;HCM;QL.19-3",
      "trunks-QL.14;HCM;QL.19-4",
      "trunks-QL.14;HCM;QL.19-5"
    ],
    "13.96_108.01__13.97_108.02": [
      "trunks-QL.14;HCM;QL.19-0",
      "trunks-QL.14;HCM;QL.19-1",
      "trunks-QL.14;HCM;QL.19-2",
      "trunks-QL.14;HCM;QL.19-3",
      "trunks-QL.14;HCM;QL.19-0",
      "trunks-QL.14;HCM;QL.19-1",
      "trunks-QL.14;HCM;QL.19-2",
      "trunks-QL.14;HCM;QL.19-3"
    ],
    "13.97_108.01__13.98_108.02": [
      "trunks-QL.14;HCM;QL.19-0",
      "trunks-QL.14;HCM;QL.19-1",
      "trunks-QL.14;HCM;QL.19-2",
      "trunks-QL.14;HCM;QL.19-3",
      "trunks-QL.14;HCM;QL.19-0",
      "trunks-QL.14;HCM;QL.19-1",
      "trunks-QL.14;HCM;QL.19-2",
      "trunks-QL.14;HCM;QL.19-3"
    ],
    "13.94_108.01__13.95_108.02": [
      "trunks-QL.14;HCM;QL.19-4",
      "trunks-QL.14;HCM;QL.19-5",
      "trunks-QL.14;HCM;QL.19-4",
      "trunks-QL.14;HCM;QL.19-5"
    ],
    "13.94_108.00__13.95_108.01": [
      "trunks-QL.14;HCM;QL.19-4",
      "trunks-QL.14;HCM;QL.19-5",
      "trunks-QL.14;HCM;QL.19-4",
      "trunks-QL.14;HCM;QL.19-5"
    ],
    "13.93_108.00__13.94_108.01": [
      "trunks-QL.14;HCM;QL.19-4",
      "trunks-QL.14;HCM;QL.19-5",
      "trunks-QL.14;HCM;QL.19-4",
      "trunks-QL.14;HCM;QL.19-5"
    ],
    "13.92_108.00__13.93_108.01": [
      "trunks-QL.14;HCM;QL.19-4",
      "trunks-QL.14;HCM;QL.19-5",
      "trunks-QL.14;HCM;QL.19-4",
      "trunks-QL.14;HCM;QL.19-5"
    ],
    "13.91_108.00__13.92_108.01": [
      "trunks-QL.14;HCM;QL.19-4",
      "trunks-QL.14;HCM;QL.19-5",
      "trunks-QL.14;HCM;QL.19-4",
      "trunks-QL.14;HCM;QL.19-5"
    ],
    "13.91_108.01__13.92_108.02": [
      "trunks-QL.14;HCM;QL.19-4",
      "trunks-QL.14;HCM;QL.19-5",
      "trunks-QL.14;HCM;QL.19-4",
      "trunks-QL.14;HCM;QL.19-5"
    ],
    "13.90_108.01__13.91_108.02": [
      "trunks-QL.14;HCM;QL.19-4",
      "trunks-QL.14;HCM;QL.19-5",
      "trunks-QL.14;HCM;QL.19-6",
      "trunks-QL.14;HCM;QL.19-4",
      "trunks-QL.14;HCM;QL.19-5",
      "trunks-QL.14;HCM;QL.19-6"
    ],
    "13.89_108.01__13.90_108.02": [
      "trunks-QL.14;HCM;QL.19-4",
      "trunks-QL.14;HCM;QL.19-5",
      "trunks-QL.14;HCM;QL.19-6",
      "trunks-QL.14;HCM;QL.19-4",
      "trunks-QL.14;HCM;QL.19-5",
      "trunks-QL.14;HCM;QL.19-6"
    ],
    "13.88_108.01__13.89_108.02": [
      "trunks-QL.14;HCM;QL.19-4",
      "trunks-QL.14;HCM;QL.19-5",
      "trunks-QL.14;HCM;QL.19-6",
      "trunks-QL.14;HCM;QL.19-4",
      "trunks-QL.14;HCM;QL.19-5",
      "trunks-QL.14;HCM;QL.19-6"
    ],
    "13.93_108.01__13.94_108.02": [
      "trunks-QL.14;HCM;QL.19-5",
      "trunks-QL.14;HCM;QL.19-5"
    ]
  },
  "highways": [
    {
      "id": 0,
      "highway_name": "Quốc lộ 37B",
      "ways": []
    },
    {
      "highway_name": "Quốc lộ QL.14;HCM;QL.19",
      "ways": [
        {
          "nodes": [
            [
              13.9077599,
              108.0143219
            ],
            [
              13.9064478,
              108.0156094
            ],
            [
              13.9049794,
              108.0168995
            ],
            [
              13.903792,
              108.017436
            ],
            [
              13.9032195,
              108.0176157
            ],
            [
              13.9025763,
              108.0177927
            ],
            [
              13.9016624,
              108.0177122
            ],
            [
              13.9004282,
              108.0171409
            ],
            [
              13.8991187,
              108.0165642
            ],
            [
              13.8982313,
              108.0161753
            ],
            [
              13.8972286,
              108.0156711
            ],
            [
              13.8954944,
              108.0149066
            ],
            [
              13.8937579,
              108.014161
            ],
            [
              13.8928752,
              108.0137479
            ],
            [
              13.8916098,
              108.0131525
            ],
            [
              13.8906541,
              108.0127206
            ],
            [
              13.8894433,
              108.0121949
            ],
            [
              13.8882586,
              108.0116853
            ],
            [
              13.887157,
              108.0111784
            ],
            [
              13.8861648,
              108.0106446
            ],
            [
              13.8860894,
              108.010886
            ],
            [
              13.886753,
              108.0110899
            ],
            [
              13.8880056,
              108.0116692
            ],
            [
              13.8890498,
              108.0121279
            ],
            [
              13.8901018,
              108.012608
            ],
            [
              13.8913905,
              108.0131981
            ],
            [
              13.8923748,
              108.0136219
            ],
            [
              13.8933069,
              108.0140564
            ],
            [
              13.8942755,
              108.0144748
            ],
            [
              13.8951763,
              108.0149066
            ],
            [
              13.8962226,
              108.0153707
            ],
            [
              13.8972932,
              108.0158454
            ],
            [
              13.8984051,
              108.0163577
            ],
            [
              13.9000739,
              108.0171061
            ],
            [
              13.9009826,
              108.0175111
            ],
            [
              13.9017637,
              108.0178383
            ],
            [
              13.9024979,
              108.0179107
            ],
            [
              13.9030082,
              108.0178437
            ],
            [
              13.9037164,
              108.0175835
            ],
            [
              13.9047761,
              108.0171651
            ],
            [
              13.9054687,
              108.0167279
            ],
            [
              13.9062524,
              108.0159688
            ],
            [
              13.9071971,
              108.0150703
            ],
            [
              13.9078848,
              108.014397
            ]
          ],
          "lanes": "0",
          "maxSpeed": "0",
          "minSpeed": "",
          "bounds": [
            [
              108.0106446,
              13.8860894
            ],
            [
              108.0179107,
              13.9078848
            ]
          ],
          "buffer_geometry": [
            [
              13.907879336412146,
              108.01425874044158
            ],
            [
              13.907873853430448,
              108.01424752471122
            ],
            [
              13.907857579320503,
              108.0142260511786
            ],
            [
              13.907837551448186,
              108.01420826106705
            ],
            [
              13.907814539474263,
              108.01419483804028
            ],
            [
              13.907789427736734,
              108.0141862979368
            ],
            [
              13.90776318126611,
              108.01418296894653
            ],
            [
              13.907736808699745,
              108.01418497899894
            ],
            [
              13.90771132352045,
              108.0141922508471
            ],
            [
              13.907687705108925,
              108.01420450503639
            ],
            [
              13.90766686110678,
              108.01422127064413
            ],
            [
              13.906357445115033,
              108.01550613754804
            ],
            [
              13.904907000652175,
              108.0167804630112
            ],
            [
              13.90374508806629,
              108.01730544770763
            ],
            [
              13.903182423042454,
              108.01748206096059
            ],
            [
              13.902564282451255,
              108.01765216532203
            ],
            [
              13.901696757127079,
              108.01757575070968
            ],
            [
              13.900483489042125,
              108.01701414062369
            ],
            [
              13.90048122688481,
              108.01701311903719
            ],
            [
              13.899171726584896,
              108.01643641962775
            ],
            [
              13.899171507872316,
              108.01643632354286
            ],
            [
              13.89828732835399,
              108.01604883539028
            ],
            [
              13.897287773399105,
              108.01554621739875
            ],
            [
              13.897281672394895,
              108.0155433408553
            ],
            [
              13.895547471997446,
              108.01477884163683
            ],
            [
              13.895546298773045,
              108.01477833117707
            ],
            [
              13.89381176094683,
              108.01403357462827
            ],
            [
              13.892931121544628,
              108.01362143946426
            ],
            [
              13.89166584612466,
              108.0130260987729
            ],
            [
              13.891663994472463,
              108.01302524481062
            ],
            [
              13.890708294248855,
              108.01259334523459
            ],
            [
              13.890706493324496,
              108.01259254738935
            ],
            [
              13.889495693050627,
              108.01206684793978
            ],
            [
              13.889495280279618,
              108.01206666955608
            ],
            [
              13.88831210758934,
              108.0115577271813
            ],
            [
              13.887215789150975,
              108.01105325808096
            ],
            [
              13.886227249169348,
              108.0105214276927
            ],
            [
              13.886203100382174,
              108.01051135926951
            ],
            [
              13.886177523134851,
              108.01050626023046
            ],
            [
              13.886151471363513,
              108.01050632074906
            ],
            [
              13.88612591670194,
              108.01051153856648
            ],
            [
              13.88610181224326,
              108.01052171907604
            ],
            [
              13.886080056993194,
              108.0105364825815
            ],
            [
              13.886061462340557,
              108.01055527845857
            ],
            [
              13.886046721795628,
              108.01057740569121
            ],
            [
              13.886036385124909,
              108.01060203901685
            ],
            [
              13.885960985166696,
              108.01084343889688
            ],
            [
              13.885955351106212,
              108.01087043283049
            ],
            [
              13.885955009368926,
              108.01089804136367
            ],
            [
              13.885959973446798,
              108.01092517449784
            ],
            [
              13.88597004735556,
              108.0109507610032
            ],
            [
              13.885984833372214,
              108.0109737907114
            ],
            [
              13.886003747737291,
              108.01099335439724
            ],
            [
              13.886026043701861,
              108.01100867967536
            ],
            [
              13.886050841009453,
              108.01101916149433
            ],
            [
              13.886705889819158,
              108.01122043439516
            ],
            [
              13.887950348924988,
              108.01179597011357
            ],
            [
              13.887952684560231,
              108.01179702309669
            ],
            [
              13.888996019079054,
              108.01225534347876
            ],
            [
              13.890047082323541,
              108.01273501655102
            ],
            [
              13.891335705566513,
              108.01332508211034
            ],
            [
              13.89133847843077,
              108.0133263137238
            ],
            [
              13.892320970627255,
              108.01374933589655
            ],
            [
              13.893251285523231,
              108.01418300427946
            ],
            [
              13.893254734504898,
              108.01418455271487
            ],
            [
              13.894220941169149,
              108.01460191941072
            ],
            [
              13.895119388194537,
              108.01503259200199
            ],
            [
              13.89512295076724,
              108.01503423556595
            ],
            [
              13.896169250526194,
              108.01549833603568
            ],
            [
              13.897238993110063,
              108.01597265644972
            ],
            [
              13.89835002370094,
              108.0164845564864
            ],
            [
              13.898351255357122,
              108.01648511638608
            ],
            [
              13.900020054969033,
              108.01723351713032
            ],
            [
              13.90002033596012,
              108.01723364275566
            ],
            [
              13.900929035749881,
              108.01763864316248
            ],
            [
              13.900931787059045,
              108.01763983236802
            ],
            [
              13.901712886887601,
              108.0179670327305
            ],
            [
              13.901750846000041,
              108.01797663624102
            ],
            [
              13.90248504595925,
              108.0180490366757
            ],
            [
              13.902514954612908,
              108.01804855393615
            ],
            [
              13.903025254650467,
              108.01798155423509
            ],
            [
              13.903053515038525,
              108.01797459386523
            ],
            [
              13.903761715177106,
              108.01771439421475
            ],
            [
              13.903764676642545,
              108.01771326572094
            ],
            [
              13.904824376863472,
              108.01729486622777
            ],
            [
              13.904846579321676,
              108.0172835947236
            ],
            [
              13.905539179532505,
              108.01684639494505
            ],
            [
              13.905561104449465,
              108.01682914692492
            ],
            [
              13.906344357274005,
              108.0160704804084
            ],
            [
              13.907288606346347,
              108.01517240969773
            ],
            [
              13.907290029271223,
              108.01517103659839
            ],
            [
              13.907977729547277,
              108.01449773662739
            ],
            [
              13.907995020521511,
              108.01447712378851
            ],
            [
              13.908008075781412,
              108.01445343183306
            ],
            [
              13.908016393619913,
              108.01442757123047
            ],
            [
              13.908019654386624,
              108.01440053579066
            ],
            [
              13.908017732771894,
              108.01437336447216
            ],
            [
              13.90801070262243,
              108.01434710145529
            ],
            [
              13.907998834103378,
              108.01432275601461
            ],
            [
              13.907982583315965,
              108.0143012637328
            ],
            [
              13.907962574769694,
              108.01428345054667
            ],
            [
              13.907939577382628,
              108.01427000100668
            ],
            [
              13.907914474932218,
              108.0142614319702
            ],
            [
              13.907888232092066,
              108.01425807273907
            ],
            [
              13.907879336412146,
              108.01425874044158
            ]
          ],
          "id": 0
        }
      ],
      "id": 1
    }
  ]
}